{
  "production": 0,
  "children": [
    {
      "production": 2880,
      "children": [
        {
          "production": 2407,
          "children": [
            {
              "production": 2411,
              "children": [
                {
                  "production": 2355,
                  "children": [
                    {
                      "production": 1703,
                      "children": [
                        {
                          "production": 430,
                          "children": [
                            {
                              "symbol": "3"
                            },
                            {
                              "symbol": "4"
                            }
                          ]
                        },
                        {
                          "symbol": "3"
                        }
                      ]
                    },
                    {
                      "production": 402,
                      "children": [
                        {
                          "production": 87,
                          "children": [
                            {
                              "symbol": "4"
                            },
                            {
                              "symbol": "3"
                            }
                          ]
                        },
                        {
                          "symbol": "4"
                        }
                      ]
                    }
                  ]
                },
                {
                  "production": 1703,
                  "children": [
                    {
                      "production": 430,
                      "children": [
                        {
                          "symbol": "3"
                        },
                        {
                          "symbol": "4"
                        }
                      ]
                    },
                    {
                      "symbol": "3"
                    }
                  ]
                }
              ]
            },
            {
              "production": 411,
              "children": [
                {
                  "production": 382,
                  "children": [
                    {
                      "production": 35,
                      "children": [
                        {
                          "production": 947,
                          "children": [
                            {
                              "production": 70,
                              "children": [
                                {
                                  "symbol": "4"
                                },
                                {
                                  "symbol": "43"
                                }
                              ]
                            },
                            {
                              "symbol": "4"
                            }
                          ]
                        },
                        {
                          "symbol": "43"
                        }
                      ]
                    },
                    {
                      "symbol": "4"
                    }
                  ]
                },
                {
                  "symbol": "43"
                }
              ]
            }
          ]
        },
        {
          "production": 181,
          "children": [
            {
              "production": 35,
              "children": [
                {
                  "production": 947,
                  "children": [
                    {
                      "production": 70,
                      "children": [
                        {
                          "symbol": "4"
                        },
                        {
                          "symbol": "43"
                        }
                      ]
                    },
                    {
                      "symbol": "4"
                    }
                  ]
                },
                {
                  "symbol": "43"
                }
              ]
            },
            {
              "symbol": "31"
            }
          ]
        }
      ]
    },
    {
      "production": 1730,
      "children": [
        {
          "symbol": "43"
        },
        {
          "symbol": "31"
        }
      ]
    },
    {
      "production": 2968,
      "children": [
        {
          "production": 2887,
          "children": [
            {
              "production": 2222,
              "children": [
                {
                  "symbol": "14"
                },
                {
                  "production": 123,
                  "children": [
                    {
                      "symbol": "32"
                    },
                    {
                      "symbol": "14"
                    }
                  ]
                }
              ]
            },
            {
              "production": 123,
              "children": [
                {
                  "symbol": "32"
                },
                {
                  "symbol": "14"
                }
              ]
            }
          ]
        },
        {
          "production": 2748,
          "children": [
            {
              "production": 3002,
              "children": [
                {
                  "production": 123,
                  "children": [
                    {
                      "symbol": "32"
                    },
                    {
                      "symbol": "14"
                    }
                  ]
                },
                {
                  "symbol": "11"
                }
              ]
            },
            {
              "production": 225,
              "children": [
                {
                  "symbol": "14"
                },
                {
                  "symbol": "11"
                }
              ]
            }
          ]
        }
      ]
    },
    {
      "production": 2969,
      "children": [
        {
          "production": 2954,
          "children": [
            {
              "production": 927,
              "children": [
                {
                  "symbol": "18"
                },
                {
                  "symbol": "11"
                }
              ]
            },
            {
              "symbol": "18"
            }
          ]
        },
        {
          "production": 1571,
          "children": [
            {
              "production": 1496,
              "children": [
                {
                  "symbol": "35"
                },
                {
                  "symbol": "18"
                }
              ]
            },
            {
              "symbol": "35"
            }
          ]
        }
      ]
    },
    {
      "production": 2768,
      "children": [
        {
          "production": 2155,
          "children": [
            {
              "production": 935,
              "children": [
                {
                  "production": 184,
                  "children": [
                    {
                      "production": 1779,
                      "children": [
                        {
                          "symbol": "17"
                        },
                        {
                          "symbol": "35"
                        }
                      ]
                    },
                    {
                      "symbol": "17"
                    }
                  ]
                },
                {
                  "symbol": "35"
                }
              ]
            },
            {
              "production": 1732,
              "children": [
                {
                  "production": 1497,
                  "children": [
                    {
                      "symbol": "17"
                    },
                    {
                      "symbol": "3"
                    }
                  ]
                },
                {
                  "symbol": "17"
                }
              ]
            }
          ]
        },
        {
          "production": 649,
          "children": [
            {
              "symbol": "3"
            },
            {
              "symbol": "8"
            }
          ]
        }
      ]
    },
    {
      "production": 2970,
      "children": [
        {
          "symbol": "23"
        },
        {
          "symbol": "17"
        }
      ]
    },
    {
      "symbol": "13"
    },
    {
      "production": 144,
      "children": [
        {
          "symbol": "17"
        },
        {
          "symbol": "18"
        }
      ]
    },
    {
      "production": 2668,
      "children": [
        {
          "production": 790,
          "children": [
            {
              "symbol": "8"
            },
            {
              "symbol": "18"
            }
          ]
        },
        {
          "production": 2166,
          "children": [
            {
              "production": 2108,
              "children": [
                {
                  "production": 1421,
                  "children": [
                    {
                      "production": 92,
                      "children": [
                        {
                          "production": 629,
                          "children": [
                            {
                              "symbol": "34"
                            },
                            {
                              "symbol": "1"
                            }
                          ]
                        },
                        {
                          "symbol": "20"
                        }
                      ]
                    },
                    {
                      "production": 254,
                      "children": [
                        {
                          "symbol": "1"
                        },
                        {
                          "symbol": "20"
                        }
                      ]
                    }
                  ]
                },
                {
                  "production": 1814,
                  "children": [
                    {
                      "symbol": "42"
                    },
                    {
                      "symbol": "20"
                    }
                  ]
                }
              ]
            },
            {
              "production": 1814,
              "children": [
                {
                  "symbol": "42"
                },
                {
                  "symbol": "20"
                }
              ]
            }
          ]
        }
      ]
    },
    {
      "production": 419,
      "children": [
        {
          "production": 149,
          "children": [
            {
              "production": 1636,
              "children": [
                {
                  "production": 1814,
                  "children": [
                    {
                      "symbol": "42"
                    },
                    {
                      "symbol": "20"
                    }
                  ]
                },
                {
                  "symbol": "42"
                }
              ]
            },
            {
              "symbol": "29"
            }
          ]
        },
        {
          "symbol": "5"
        }
      ]
    },
    {
      "production": 2111,
      "children": [
        {
          "production": 1184,
          "children": [
            {
              "production": 392,
              "children": [
                {
                  "production": 3735,
                  "children": [
                    {
                      "production": 702,
                      "children": [
                        {
                          "symbol": "2"
                        },
                        {
                          "symbol": "0"
                        }
                      ]
                    },
                    {
                      "symbol": "2"
                    }
                  ]
                },
                {
                  "symbol": "0"
                }
              ]
            },
            {
              "symbol": "2"
            }
          ]
        },
        {
          "symbol": "0"
        }
      ]
    },
    {
      "production": 2971,
      "children": [
        {
          "production": 2994,
          "children": [
            {
              "production": 2111,
              "children": [
                {
                  "production": 1184,
                  "children": [
                    {
                      "production": 392,
                      "children": [
                        {
                          "production": 3735,
                          "children": [
                            {
                              "production": 702,
                              "children": [
                                {
                                  "symbol": "2"
                                },
                                {
                                  "symbol": "0"
                                }
                              ]
                            },
                            {
                              "symbol": "2"
                            }
                          ]
                        },
                        {
                          "symbol": "0"
                        }
                      ]
                    },
                    {
                      "symbol": "2"
                    }
                  ]
                },
                {
                  "symbol": "0"
                }
              ]
            },
            {
              "production": 1621,
              "children": [
                {
                  "production": 318,
                  "children": [
                    {
                      "symbol": "7"
                    },
                    {
                      "symbol": "0"
                    }
                  ]
                },
                {
                  "symbol": "7"
                }
              ]
            }
          ]
        },
        {
          "symbol": "0"
        }
      ]
    },
    {
      "production": 1623,
      "children": [
        {
          "production": 846,
          "children": [
            {
              "symbol": "33"
            },
            {
              "symbol": "24"
            }
          ]
        },
        {
          "production": 1400,
          "children": [
            {
              "symbol": "29"
            },
            {
              "symbol": "24"
            }
          ]
        }
      ]
    },
    {
      "production": 1793,
      "children": [
        {
          "production": 82,
          "children": [
            {
              "production": 3736,
              "children": [
                {
                  "symbol": "19"
                },
                {
                  "symbol": "10"
                }
              ]
            },
            {
              "symbol": "27"
            }
          ]
        },
        {
          "production": 958,
          "children": [
            {
              "symbol": "10"
            },
            {
              "symbol": "27"
            }
          ]
        }
      ]
    },
    {
      "production": 1145,
      "children": [
        {
          "production": 421,
          "children": [
            {
              "symbol": "19"
            },
            {
              "symbol": "27"
            }
          ]
        },
        {
          "production": 421,
          "children": [
            {
              "symbol": "19"
            },
            {
              "symbol": "27"
            }
          ]
        }
      ]
    },
    {
      "production": 377,
      "children": [
        {
          "symbol": "10"
        },
        {
          "symbol": "19"
        }
      ]
    },
    {
      "symbol": "29"
    },
    {
      "production": 2650,
      "children": [
        {
          "production": 2623,
          "children": [
            {
              "production": 3036,
              "children": [
                {
                  "production": 2561,
                  "children": [
                    {
                      "production": 3024,
                      "children": [
                        {
                          "symbol": "16"
                        },
                        {
                          "symbol": "6"
                        }
                      ]
                    },
                    {
                      "symbol": "16"
                    }
                  ]
                },
                {
                  "production": 2081,
                  "children": [
                    {
                      "symbol": "6"
                    },
                    {
                      "symbol": "16"
                    }
                  ]
                }
              ]
            },
            {
              "production": 2598,
              "children": [
                {
                  "production": 2351,
                  "children": [
                    {
                      "symbol": "6"
                    },
                    {
                      "symbol": "26"
                    }
                  ]
                },
                {
                  "symbol": "25"
                }
              ]
            }
          ]
        },
        {
          "production": 2539,
          "children": [
            {
              "production": 2965,
              "children": [
                {
                  "production": 2607,
                  "children": [
                    {
                      "production": 505,
                      "children": [
                        {
                          "symbol": "38"
                        },
                        {
                          "symbol": "26"
                        }
                      ]
                    },
                    {
                      "symbol": "38"
                    }
                  ]
                },
                {
                  "production": 707,
                  "children": [
                    {
                      "production": 340,
                      "children": [
                        {
                          "symbol": "26"
                        },
                        {
                          "symbol": "38"
                        }
                      ]
                    },
                    {
                      "symbol": "26"
                    }
                  ]
                }
              ]
            },
            {
              "production": 505,
              "children": [
                {
                  "symbol": "38"
                },
                {
                  "symbol": "26"
                }
              ]
            }
          ]
        }
      ]
    },
    {
      "symbol": "36"
    },
    {
      "production": 2972,
      "children": [
        {
          "symbol": "14"
        },
        {
          "symbol": "36"
        }
      ]
    },
    {
      "production": 734,
      "children": [
        {
          "symbol": "30"
        },
        {
          "symbol": "37"
        }
      ]
    },
    {
      "production": 2973,
      "children": [
        {
          "production": 2762,
          "children": [
            {
              "production": 2257,
              "children": [
                {
                  "production": 1715,
                  "children": [
                    {
                      "production": 417,
                      "children": [
                        {
                          "symbol": "41"
                        },
                        {
                          "symbol": "37"
                        }
                      ]
                    },
                    {
                      "symbol": "41"
                    }
                  ]
                },
                {
                  "symbol": "40"
                }
              ]
            },
            {
              "production": 1121,
              "children": [
                {
                  "symbol": "41"
                },
                {
                  "symbol": "40"
                }
              ]
            }
          ]
        },
        {
          "production": 716,
          "children": [
            {
              "production": 3295,
              "children": [
                {
                  "production": 1121,
                  "children": [
                    {
                      "symbol": "41"
                    },
                    {
                      "symbol": "40"
                    }
                  ]
                },
                {
                  "production": 1121,
                  "children": [
                    {
                      "symbol": "41"
                    },
                    {
                      "symbol": "40"
                    }
                  ]
                }
              ]
            },
            {
              "production": 1121,
              "children": [
                {
                  "symbol": "41"
                },
                {
                  "symbol": "40"
                }
              ]
            }
          ]
        }
      ]
    },
    {
      "production": 2974,
      "children": [
        {
          "symbol": "38"
        },
        {
          "production": 3249,
          "children": [
            {
              "production": 2082,
              "children": [
                {
                  "symbol": "40"
                },
                {
                  "symbol": "21"
                }
              ]
            },
            {
              "symbol": "40"
            }
          ]
        }
      ]
    },
    {
      "production": 2974,
      "children": [
        {
          "symbol": "38"
        },
        {
          "production": 3249,
          "children": [
            {
              "production": 2082,
              "children": [
                {
                  "symbol": "40"
                },
                {
                  "symbol": "21"
                }
              ]
            },
            {
              "symbol": "40"
            }
          ]
        }
      ]
    },
    {
      "production": 2208,
      "children": [
        {
          "production": 2164,
          "children": [
            {
              "production": 1089,
              "children": [
                {
                  "production": 738,
                  "children": [
                    {
                      "production": 116,
                      "children": [
                        {
                          "symbol": "21"
                        },
                        {
                          "symbol": "30"
                        }
                      ]
                    },
                    {
                      "symbol": "21"
                    }
                  ]
                },
                {
                  "production": 136,
                  "children": [
                    {
                      "symbol": "30"
                    },
                    {
                      "symbol": "21"
                    }
                  ]
                }
              ]
            },
            {
              "symbol": "30"
            }
          ]
        },
        {
          "production": 738,
          "children": [
            {
              "production": 116,
              "children": [
                {
                  "symbol": "21"
                },
                {
                  "symbol": "30"
                }
              ]
            },
            {
              "symbol": "21"
            }
          ]
        }
      ]
    },
    {
      "production": 2756,
      "children": [
        {
          "production": 2056,
          "children": [
            {
              "production": 2098,
              "children": [
                {
                  "production": 136,
                  "children": [
                    {
                      "symbol": "30"
                    },
                    {
                      "symbol": "21"
                    }
                  ]
                },
                {
                  "symbol": "30"
                }
              ]
            },
            {
              "production": 116,
              "children": [
                {
                  "symbol": "21"
                },
                {
                  "symbol": "30"
                }
              ]
            }
          ]
        },
        {
          "production": 265,
          "children": [
            {
              "production": 25,
              "children": [
                {
                  "symbol": "39"
                },
                {
                  "symbol": "30"
                }
              ]
            },
            {
              "symbol": "39"
            }
          ]
        }
      ]
    },
    {
      "production": 570,
      "children": [
        {
          "production": 429,
          "children": [
            {
              "production": 222,
              "children": [
                {
                  "production": 139,
                  "children": [
                    {
                      "symbol": "23"
                    },
                    {
                      "symbol": "39"
                    }
                  ]
                },
                {
                  "symbol": "23"
                }
              ]
            },
            {
              "symbol": "39"
            }
          ]
        },
        {
          "symbol": "23"
        }
      ]
    }
  ]
}